multi_dice/__init__.py
multi_dice/dice.py
multi_dice/test.py
multi_dice-1.0.1.dist-info/METADATA
multi_dice-1.0.1.dist-info/WHEEL
multi_dice-1.0.1.dist-info/licenses/LICENSE
multi_dice-1.0.1.dist-info/RECORD
