Metadata-Version: 2.1
Name: multi_dice
Version: 1.0.1
Summary: A dice rolling package focused on flexibility
Project-URL: Homepage, https://github.com/BigBrainTime/multiDice
Project-URL: Issues, https://github.com/BigBrainTime/multiDice/issues
Author: BigBrainTime
License-File: LICENSE
Classifier: License :: OSI Approved :: MIT License
Classifier: Operating System :: OS Independent
Classifier: Programming Language :: Python :: 3
Requires-Python: >=3.8
